nsync/logging.py
nsync/models.py
nsync/actions.py
nsync/__init__.py
nsync/policies.py
nsync/migrations/__init__.py
nsync/migrations/0001_initial.py
nsync/management/__init__.py
nsync/management/commands/__init__.py
nsync/management/commands/syncfile.py
nsync/management/commands/utils.py
nsync/management/commands/syncfiles.py
django_nsync-0.4.0.dist-info/RECORD
django_nsync-0.4.0.dist-info/metadata.json
django_nsync-0.4.0.dist-info/WHEEL
django_nsync-0.4.0.dist-info/DESCRIPTION.rst
django_nsync-0.4.0.dist-info/pbr.json
django_nsync-0.4.0.dist-info/top_level.txt
django_nsync-0.4.0.dist-info/METADATA
